Metadata-Version: 2.1
Name: collective.sidebar
Version: 1.5.0
Summary: A sidebar for Plone to consolidate toolbar and navigation.
Home-page: https://pypi.python.org/pypi/collective.sidebar
Author: Stefan Antonelli
Author-email: stefan.antonelli@operun.de
License: GPL version 2
Keywords: Python Plone
Platform: UNKNOWN
Classifier: Environment :: Web Environment
Classifier: Framework :: Plone
Classifier: Framework :: Plone :: 5.2
Classifier: Programming Language :: Python
Classifier: Programming Language :: Python :: 3.7
Classifier: Operating System :: OS Independent
Classifier: License :: OSI Approved :: GNU General Public License v2 (GPLv2)
Provides-Extra: test
